version_control/__init__.py
version_control/admin.py
version_control/apps.py
version_control/cache.py
version_control/collections.py
version_control/database.py
version_control/debugger.py
version_control/export.py
version_control/forms.py
version_control/managers.py
version_control/middleware.py
version_control/mixins.py
version_control/models.py
version_control/serializers.py
version_control/service.py
version_control/signals.py
version_control/tasks.py
version_control/tests.py
version_control/urls.py
version_control/utils.py
version_control/views.py
version_control/management/__init__.py
version_control/management/commands/__init__.py
version_control/management/commands/initialize_version_control.py
version_control/migrations/0001_initial.py
version_control/migrations/__init__.py
version_control/templates/admin/version_control/modelobjectversion/change_form.html
version_control/templates/admin/version_control/modelobjectversion/change_list.html
version_control/templates/admin/version_control/modelobjectversiongroup/change_form.html
version_control/templates/admin/version_control/modelobjectversiongroup/vcs_relation_tree.html
version_control/templatetags/__init__.py
version_control/templatetags/version_control.py
btc_version_manager-0.4.1.dist-info/LICENSE
btc_version_manager-0.4.1.dist-info/METADATA
btc_version_manager-0.4.1.dist-info/WHEEL
btc_version_manager-0.4.1.dist-info/top_level.txt
btc_version_manager-0.4.1.dist-info/RECORD
