Metadata-Version: 2.1
Name: btc-version-manager
Version: 0.4.1
Summary: App that add functionality to track model object versions for any other Django application.
Home-page: https://github.com/MEADez/btc-version-manager
Author: MEADez
Author-email: m3adez@gmail.com
License: BSD License
Platform: UNKNOWN
Classifier: Environment :: Web Environment
Classifier: Framework :: Django
Classifier: Intended Audience :: Developers
Classifier: License :: OSI Approved :: BSD License
Classifier: Operating System :: OS Independent
Classifier: Programming Language :: Python :: 3.6
Classifier: Topic :: Internet :: WWW/HTTP
Classifier: Topic :: Internet :: WWW/HTTP :: Dynamic Content
Requires-Dist: psycopg2-binary (>=2.7.6.1)
Requires-Dist: Django (>=2.1.4)
